plotastic/__init__.py
plotastic/caches.py
plotastic/docstrings.py
plotastic/py.typed
plotastic/dataanalysis/__init__.py
plotastic/dataanalysis/annotator.py
plotastic/dataanalysis/dataanalysis.py
plotastic/dataanalysis/filer.py
plotastic/dimensions/__init__.py
plotastic/dimensions/dataframetool.py
plotastic/dimensions/dataintegrity.py
plotastic/dimensions/dims.py
plotastic/dimensions/dimsandlevels.py
plotastic/dimensions/hierarchical_dims.py
plotastic/dimensions/subject.py
plotastic/example_data/__init__.py
plotastic/example_data/load_dataset.py
plotastic/example_data/data/fmri.xlsx
plotastic/example_data/data/qpcr.xlsx
plotastic/example_data/data/tips.xlsx
plotastic/plotting/__init__.py
plotastic/plotting/multiplot.py
plotastic/plotting/plot.py
plotastic/plotting/plotedits.py
plotastic/plotting/rc.py
plotastic/plotting/rc_utils.py
plotastic/plotting/subplot.py
plotastic/stat/__init__.py
plotastic/stat/assumptions.py
plotastic/stat/bivariate.py
plotastic/stat/omnibus.py
plotastic/stat/posthoc.py
plotastic/stat/statresults.py
plotastic/stat/stattest.py
plotastic/utils/__init__.py
plotastic/utils/subcache.py
plotastic/utils/utils.py
plotastic-0.1.1.dist-info/LICENSE
plotastic-0.1.1.dist-info/METADATA
plotastic-0.1.1.dist-info/WHEEL
plotastic-0.1.1.dist-info/top_level.txt
plotastic-0.1.1.dist-info/RECORD
