Metadata-Version: 2.1
Name: plotastic
Version: 0.1.1
Summary: Streamlining statistical analysis by using plotting keywords in Python.
Author-email: Martin Kuric <martin.kur4@gmail.com>
License: GNU GENERAL PUBLIC LICENSE
Project-URL: Homepage, https://github.com/markur4/plotastic
Project-URL: Documentation, https://github.com/markur4/plotastic
Project-URL: Source Code, https://github.com/markur4/plotastic
Project-URL: Bug Reports, https://github.com/markur4/plotastic/issues
Keywords: plotting,statistics,data analysis,data visualization,data science,data,science,visualization
Classifier: License :: OSI Approved :: GNU General Public License v3 (GPLv3)
Classifier: Development Status :: 5 - Production/Stable
Classifier: Framework :: IPython
Classifier: Framework :: Jupyter
Classifier: Intended Audience :: Science/Research
Classifier: Intended Audience :: Education
Classifier: Intended Audience :: Healthcare Industry
Classifier: Intended Audience :: Financial and Insurance Industry
Classifier: Topic :: Scientific/Engineering
Classifier: Topic :: Scientific/Engineering :: Visualization
Classifier: Topic :: Scientific/Engineering :: Information Analysis
Classifier: Topic :: Scientific/Engineering :: Bio-Informatics
Classifier: Programming Language :: Python :: 3.11
Requires-Python: >=3.11
License-File: LICENSE
Requires-Dist: numpy
Requires-Dist: pandas ==1.5.3
Requires-Dist: matplotlib
Requires-Dist: seaborn <=0.12.2
Requires-Dist: Pillow >=10.2.0
Requires-Dist: scipy
Requires-Dist: statannotations
Requires-Dist: pingouin
Requires-Dist: xlsxwriter
Requires-Dist: openpyxl
Requires-Dist: joblib
Requires-Dist: colour
Requires-Dist: ipynbname
Requires-Dist: icecream
Provides-Extra: dev
Requires-Dist: pytest ; extra == 'dev'
Requires-Dist: ipytest ; extra == 'dev'
Requires-Dist: pytest-cov ; extra == 'dev'
Requires-Dist: pytest-xdist ; extra == 'dev'
Requires-Dist: nbconvert ; extra == 'dev'
Requires-Dist: build ; extra == 'dev'
Requires-Dist: twine ; extra == 'dev'
